{
  "project_info": {
    "project_number": "773266776434",
    "project_id": "kimbo-e6675",
    "storage_bucket": "kimbo-e6675.firebasestorage.app"
  },
  "client": [
    {
      "client_info": {
        "mobilesdk_app_id": "1:773266776434:android:8ce4fabdc55f931acbbdeb",
        "android_client_info": {
          "package_name": "com.Kimbo"
        }
      },
      "oauth_client": [],
      "api_key": [
        {
          "current_key": "AIzaSyCtz_gFfHaokcPw2HlfP3Awjx1MB6ZlJaI"
        }
      ],
      "services": {
        "appinvite_service": {
          "other_platform_oauth_client": []
        }
      }
    }
  ],
  "configuration_version": "1"
}